ghtool/__init__.py
ghtool/cli.py
ghtool/cmd_line.py
ghtool/commands.py
ghtool/exceptions.py
ghtool/ghtool.py
ghtool/parser.py
ghtool-0.2.dist-info/DESCRIPTION.rst
ghtool-0.2.dist-info/METADATA
ghtool-0.2.dist-info/RECORD
ghtool-0.2.dist-info/WHEEL
ghtool-0.2.dist-info/entry_points.txt
ghtool-0.2.dist-info/metadata.json
ghtool-0.2.dist-info/top_level.txt
